{
  "version": "2.0",
  "identity_profile": "Aspire_5800H_ab96",
  "hostname": "aspire-7-fa35",
  "_id_suffix": "e1",
  "hardware": {
    "machine_id": "464b5d13866aa8589c887e0b6fe18599",
    "product_uuid": "1bcf43cd-d9d3-38f1-7cd4-0861f4b6ca97",
    "product_serial": "SN-ASPIDA2543",
    "board_serial": "MB-477738",
    "chassis_serial": "CH-0EE0B4",
    "product_name": "Aspire A515-45",
    "board_name": "Charmeleon_CFS",
    "board_vendor": "Acer",
    "bios_vendor": "Insyde",
    "bios_version": "V1.14",
    "bios_date": "08/30/2021"
  },
  "cpu": {
    "model": "AMD Ryzen 7 5800H with Radeon Graphics",
    "cores": 8,
    "threads": 16,
    "vendor_id": "AuthenticAMD",
    "mhz": "3200.000",
    "cache_size": "16384 KB"
  },
  "network": {
    "interfaces": {
      "eth0": "28:7f:cf",
      "wlan0": "28:7f:cf"
    }
  },
  "storage": {
    "sda_serial": "AJ85N6579EBDD2",
    "nvme_serial": "AJ85N657050F0A",
    "sda_model": "SK hynix Gold P31 1TB",
    "nvme_model": "SK hynix Gold P31 1TB"
  },
  "os": {
    "name": "Manjaro Linux",
    "version": "23.1.0",
    "kernel_release": "6.5.9-1-MANJARO",
    "kernel_version": "#1 SMP PREEMPT_DYNAMIC Tue Nov 7 10:00:00 UTC 2023"
  },
  "gpu": {
    "nvidia_vendor": "0x10de",
    "nvidia_device": "0x2482",
    "intel_vendor": "0x8086",
    "intel_device": "0x3e9b"
  },
  "boot": {
    "boot_id": "9d592bde-2d37-3044-acbd-b3cfa080d7f7",
    "random_uuid": "2bb10176-0855-5cb1-50b8-b199521d4fe6"
  },
  "environment": {
    "locale": "de_DE.UTF-8",
    "language": "de_DE:de",
    "timezone": "Europe/London",
    "display": ":0"
  },
  "battery": {
    "has_battery": true,
    "manufacturer": "Celxpert",
    "model": "L19C3PD6",
    "technology": "Li-poly",
    "capacity_wh": 52.5,
    "voltage_v": 11.52,
    "cells": 3
  },
  "memory": {
    "size_gb": 8,
    "size_kb": 8192000,
    "speed_mhz": 3733,
    "type": "LPDDR4X",
    "manufacturer": "SK hynix",
    "model": "H9HCNNNBKMMLXR"
  },
  "display": {
    "name": "eDP-1",
    "resolution": "2880x1800",
    "width": 2880,
    "height": 1800,
    "refresh_rate": 90,
    "manufacturer": "Samsung",
    "model": "ATNA40YK01",
    "diagonal_inches": 14.0,
    "panel_type": "OLED"
  },
  "_metadata": {
    "generated_by": "formulate_identity.py",
    "strategy": "moderate",
    "components_used": {
      "cpu": "cpu_amd_ryzen_7_5800h",
      "gpu": "gpu_nvidia_rtx3070ti",
      "motherboard": "mb_acer_aspire_5",
      "network": "net_intel_ax210",
      "storage": "ssd_sk_hynix_p31",
      "os": "os_manjaro_23"
    }
  }
}